Mashup/__init__.py
Mashup/__main__.py
Mashup_Samarjot_102003242-1.0.1.dist-info/Licence.txt
Mashup_Samarjot_102003242-1.0.1.dist-info/METADATA
Mashup_Samarjot_102003242-1.0.1.dist-info/WHEEL
Mashup_Samarjot_102003242-1.0.1.dist-info/entry_points.txt
Mashup_Samarjot_102003242-1.0.1.dist-info/top_level.txt
Mashup_Samarjot_102003242-1.0.1.dist-info/RECORD
