Metadata-Version: 2.1
Name: Mashup-Samarjot-102003242
Version: 1.0.1
Summary: Python package creating Mashup of multiple songs.
Author: Samarjot Singh
Author-email: 2001samar@gmail.com
License: MIT
Classifier: License :: OSI Approved :: MIT License
Classifier: Programming Language :: Python :: 3
Classifier: Programming Language :: Python :: 3.11
License-File: Licence.txt
Requires-Dist: pytube
Requires-Dist: pydub
